json_toon/__init__.py
json_toon/converter.py
json_toon-1.0.2.dist-info/licenses/LICENSE
json_toon-1.0.2.dist-info/METADATA
json_toon-1.0.2.dist-info/WHEEL
json_toon-1.0.2.dist-info/top_level.txt
json_toon-1.0.2.dist-info/RECORD
