Metadata-Version: 2.4
Name: json-toon
Version: 1.0.2
Summary: Convert Python data to TOON (Token-Oriented Object Notation) - A lightweight, LLM-friendly structured data format
Author-email: Monish Meher <monishmeher@gmail.com>
License-Expression: MIT
Project-URL: Homepage, https://github.com/CatalystMeher/json_toon
Keywords: json,toon,converter,llm,prompt
Requires-Python: >=3.8
License-File: LICENSE
Dynamic: license-file
